{
  "type": "Feature",
  "stac_version": "1.0.0",
  "stac_extensions": [
    "https://stac-extensions.github.io/view/v1.0.0/schema.json",
    "https://stac-extensions.github.io/sar/v1.0.0/schema.json"
  ],
  "id": "587eb484-4788-4eff-a1f3-c22109891a29",
  "geometry": {
    "type": "Polygon",
    "coordinates": [
      [
        [
          29.37877775553882,
          -1.339194292453695,
          1568.9932922683656
        ],
        [
          29.379266561409366,
          -1.334699672530657,
          1569.0522414604202
        ],
        [
          29.379755624428462,
          -1.3302043938766153,
          1569.1506757298484
        ],
        [
          29.380244519287192,
          -1.3257122777744452,
          1569.2884785952047
        ],
        [
          29.375779162687174,
          -1.3252193696878403,
          1569.1513623706996
        ],
        [
          29.37131514205307,
          -1.3247293160535194,
          1569.0533785438165
        ],
        [
          29.366849587542998,
          -1.324234579903689,
          1568.994702577591
        ],
        [
          29.362385362841994,
          -1.3237427026117607,
          1568.97513718158
        ],
        [
          29.357918744354606,
          -1.3232538116387356,
          1568.9946531876922
        ],
        [
          29.353454306429605,
          -1.3227601148469137,
          1569.0535274688154
        ],
        [
          29.348991187266805,
          -1.3222692879194773,
          1569.15144814644
        ],
        [
          29.344526096742374,
          -1.3217776145383837,
          1569.2886173073202
        ],
        [
          29.34403691177962,
          -1.326272181185989,
          1569.1505494639277
        ],
        [
          29.343547967882337,
          -1.330766084990764,
          1569.0519481860101
        ],
        [
          29.343059262604474,
          -1.3352593316957975,
          1568.9927955484018
        ],
        [
          29.34257079373995,
          -1.3397519270870224,
          1568.9730738224462
        ],
        [
          29.342082146383213,
          -1.344247715727912,
          1568.9927990203723
        ],
        [
          29.341594146441025,
          -1.3487390250468174,
          1569.0519203608856
        ],
        [
          29.341102257407304,
          -1.3532336691240279,
          1569.1506635323167
        ],
        [
          29.340614315107945,
          -1.357727553911001,
          1569.2886983379722
        ],
        [
          29.345079328889373,
          -1.358220636200358,
          1569.151773638092
        ],
        [
          29.349546082697117,
          -1.3587127341114116,
          1569.0539715122432
        ],
        [
          29.354010864227458,
          -1.3592039813732053,
          1568.9953851494938
        ],
        [
          29.358473673432805,
          -1.3596943788406572,
          1568.9759608209133
        ],
        [
          29.362941548173744,
          -1.3601874830381588,
          1568.9958060756326
        ],
        [
          29.36740373580084,
          -1.3606798693635884,
          1569.0547891100869
        ],
        [
          29.371871399087688,
          -1.3611711294916633,
          1569.1529927803203
        ],
        [
          29.376337099139732,
          -1.361661535824474,
          1569.2903368854895
        ],
        [
          29.376824651619426,
          -1.3571701233071334,
          1569.1520919054747
        ],
        [
          29.37731285675051,
          -1.3526742579778372,
          1569.0531768249348
        ],
        [
          29.377800905514682,
          -1.3481815793970702,
          1568.9937775675207
        ],
        [
          29.378289204366318,
          -1.34368825948692,
          1568.9738102117553
        ],
        [
          29.37877775553882,
          -1.339194292453695,
          1568.9932922683656
        ]
      ]
    ]
  },
  "bbox": [
    29.340614315107945,
    -1.361661535824474,
    29.380244519287192,
    -1.3217776145383837
  ],
  "properties": {
    "created": "2024-12-17T09:50:47.030414Z",
    "updated": "2024-12-17T09:50:47.030414Z",
    "start_datetime": "2023-08-04T19:15:18Z",
    "end_datetime": "2023-08-04T19:15:21.120867Z",
    "license": "CC-BY-4.0",
    "providers": [
      {
        "name": "umbra",
        "roles": [
          "host",
          "processor",
          "producer",
          "licensor"
        ],
        "url": "https://umbra.space"
      }
    ],
    "constellation": "umbra",
    "platform": "UMBRA_05",
    "mission": "umbra-sample-data",
    "view:incidence_angle": 49.38779237407578,
    "sar:instrument_mode": "SPOTLIGHT",
    "sar:frequency_band": "X",
    "sar:center_frequency": 9.59999621892348,
    "sar:polarizations": [
      "VV"
    ],
    "sar:product_type": "GEC",
    "sar:resolution_range": 0.45787038436525046,
    "sar:resolution_azimuth": 0.4645893705940068,
    "sar:looks_range": 1,
    "sar:looks_azimuth": 1,
    "sar:observation_direction": "left",
    "datetime": "2023-08-04T19:15:18Z"
  },
  "links": [
    {
      "rel": "root",
      "href": "../../../../catalog.json",
      "type": "application/json",
      "title": "Umbra Open SAR Data"
    },
    {
      "rel": "parent",
      "href": "../catalog.json",
      "type": "application/json",
      "title": "2023-08-04"
    }
  ],
  "assets": {
    "metadata": {
      "href": "http://umbra-open-data-catalog.s3.amazonaws.com/sar-data/tasks/Rumangabo%2C%20DRC/3b9abc28-9da5-4e92-a315-a85ca4fb2454/2023-08-04-19-15-17_UMBRA-05/2023-08-04-19-15-17_UMBRA-05_METADATA.json",
      "type": "application/json",
      "title": "metadata",
      "description": "Extended Umbra Metadata: https://docs.canopy.umbra.space/reference/get_schema",
      "roles": [
        "metadata"
      ]
    },
    "CPHD": {
      "href": "https://umbra-open-data-catalog.s3.amazonaws.com/sar-data/tasks/Rumangabo, DRC/3b9abc28-9da5-4e92-a315-a85ca4fb2454/2023-08-04-19-15-17_UMBRA-05/2023-08-04-19-15-17_UMBRA-05_CPHD.cphd",
      "type": "application/octet-stream",
      "title": "CPHD",
      "description": "https://nsgreg.nga.mil/doc/view?i=4638",
      "roles": [
        "data"
      ]
    },
    "GEC": {
      "href": "https://umbra-open-data-catalog.s3.amazonaws.com/sar-data/tasks/Rumangabo, DRC/3b9abc28-9da5-4e92-a315-a85ca4fb2454/2023-08-04-19-15-17_UMBRA-05/2023-08-04-19-15-17_UMBRA-05_GEC.tif",
      "type": "image/tiff; application=geotiff; profile=cloud-optimized",
      "title": "GEC",
      "roles": [
        "data",
        "overview"
      ]
    },
    "SICD": {
      "href": "https://umbra-open-data-catalog.s3.amazonaws.com/sar-data/tasks/Rumangabo, DRC/3b9abc28-9da5-4e92-a315-a85ca4fb2454/2023-08-04-19-15-17_UMBRA-05/2023-08-04-19-15-17_UMBRA-05_SICD.nitf",
      "type": "application/vnd.nitf",
      "title": "SICD",
      "description": "Sensor Independent Complex Data",
      "roles": [
        "data"
      ]
    },
    "SIDD": {
      "href": "https://umbra-open-data-catalog.s3.amazonaws.com/sar-data/tasks/Rumangabo, DRC/3b9abc28-9da5-4e92-a315-a85ca4fb2454/2023-08-04-19-15-17_UMBRA-05/2023-08-04-19-15-17_UMBRA-05_SIDD.nitf",
      "type": "application/vnd.nitf",
      "title": "SIDD",
      "description": "Sensor Independent Derived Data",
      "roles": [
        "data"
      ]
    }
  }
}