{
  "type": "Feature",
  "stac_version": "1.0.0",
  "stac_extensions": [
    "https://stac-extensions.github.io/view/v1.0.0/schema.json",
    "https://stac-extensions.github.io/sar/v1.0.0/schema.json"
  ],
  "id": "5aa168f9-06be-4f92-91fe-5724154b9ab7",
  "geometry": {
    "type": "Polygon",
    "coordinates": [
      [
        [
          -96.8658958757398,
          46.90457490315442,
          248.28619076590985
        ],
        [
          -96.86128961764173,
          46.901371322338505,
          248.14903455320746
        ],
        [
          -96.85670069896375,
          46.89815848583139,
          248.0516055431217
        ],
        [
          -96.85210286627621,
          46.89495415688397,
          247.99298236705363
        ],
        [
          -96.84749376234988,
          46.89174281738528,
          247.97346069663763
        ],
        [
          -96.8429043295337,
          46.8885377403693,
          247.99330618884414
        ],
        [
          -96.83830363074567,
          46.88532565065699,
          248.05238071549684
        ],
        [
          -96.83370712875633,
          46.88211318438255,
          248.15074300952256
        ],
        [
          -96.8291302470833,
          46.878906978160224,
          248.28802819550037
        ],
        [
          -96.82442816248442,
          46.88205646323922,
          248.150714058429
        ],
        [
          -96.81976011471596,
          46.88520483845487,
          248.05250274948776
        ],
        [
          -96.81506894092442,
          46.88835666598097,
          247.99350620340556
        ],
        [
          -96.81038321785061,
          46.89150966690433,
          247.97365879733115
        ],
        [
          -96.80571602759738,
          46.89465491626017,
          247.99280256126076
        ],
        [
          -96.80102572179608,
          46.897803646900925,
          248.05146294925362
        ],
        [
          -96.79634083949902,
          46.900953556627094,
          248.14916949905455
        ],
        [
          -96.79166137372765,
          46.90410464430077,
          248.28587134275585
        ],
        [
          -96.7962592385085,
          46.907315306949315,
          248.14890306442976
        ],
        [
          -96.80083278590946,
          46.91052790413809,
          248.05179947894067
        ],
        [
          -96.80543902474184,
          46.91373778351883,
          247.99299544561654
        ],
        [
          -96.81004946274469,
          46.91694727453341,
          247.9733884446323
        ],
        [
          -96.81463559538268,
          46.92015869163824,
          247.99345724191517
        ],
        [
          -96.81922593496837,
          46.923369714671416,
          248.05259736906737
        ],
        [
          -96.82382048871978,
          46.926580344603025,
          248.15085068438202
        ],
        [
          -96.8284192637722,
          46.92979058236305,
          248.28825924079865
        ],
        [
          -96.83312161082091,
          46.92663937754841,
          248.15084410831332
        ],
        [
          -96.83780088392669,
          46.92349165753923,
          248.0527212349698
        ],
        [
          -96.84248312491417,
          46.92032961465773,
          247.9933074582368
        ],
        [
          -96.84717333288897,
          46.91718426199085,
          247.97376285493374
        ],
        [
          -96.85185349267853,
          46.91403347234377,
          247.99309297371656
        ],
        [
          -96.85653913463143,
          46.9108838607693,
          248.05174829997122
        ],
        [
          -96.86121475388165,
          46.907728796321756,
          248.14928015321493
        ],
        [
          -96.8658958757398,
          46.90457490315442,
          248.28619076590985
        ]
      ]
    ]
  },
  "bbox": [
    -96.8658958757398,
    46.878906978160224,
    -96.79166137372765,
    46.92979058236305
  ],
  "properties": {
    "created": "2024-12-17T09:49:30.332318Z",
    "updated": "2024-12-17T09:49:30.332318Z",
    "start_datetime": "2023-10-10T16:55:05Z",
    "end_datetime": "2023-10-10T16:55:06Z",
    "license": "CC-BY-4.0",
    "providers": [
      {
        "name": "umbra",
        "roles": [
          "host",
          "processor",
          "producer",
          "licensor"
        ],
        "url": "https://umbra.space"
      }
    ],
    "constellation": "umbra",
    "platform": "UMBRA_04",
    "mission": "umbra-sample-data",
    "view:incidence_angle": 49.62726143470798,
    "sar:instrument_mode": "SPOTLIGHT",
    "sar:frequency_band": "X",
    "sar:center_frequency": 9.599996927718166,
    "sar:polarizations": [
      "VV"
    ],
    "sar:product_type": "GEC",
    "sar:resolution_range": 1.5146682668859246,
    "sar:resolution_azimuth": 1.555365521531382,
    "sar:looks_range": 1,
    "sar:looks_azimuth": 1,
    "sar:observation_direction": "left",
    "datetime": "2023-10-10T16:55:05Z"
  },
  "links": [
    {
      "rel": "root",
      "href": "../../../../catalog.json",
      "type": "application/json",
      "title": "Umbra Open SAR Data"
    },
    {
      "rel": "parent",
      "href": "../catalog.json",
      "type": "application/json",
      "title": "2023-10-10"
    }
  ],
  "assets": {
    "metadata": {
      "href": "http://umbra-open-data-catalog.s3.amazonaws.com/sar-data/tasks/North%20Dakota%20State%20University%20Plot/9eca8179-ed29-4af4-a9eb-8d1603bc4942/2023-10-10-16-55-04_UMBRA-04/2023-10-10-16-55-04_UMBRA-04_METADATA.json",
      "type": "application/json",
      "title": "metadata",
      "description": "Extended Umbra Metadata: https://docs.canopy.umbra.space/reference/get_schema",
      "roles": [
        "metadata"
      ]
    },
    "CPHD": {
      "href": "https://umbra-open-data-catalog.s3.amazonaws.com/sar-data/tasks/North Dakota State University Plot/9eca8179-ed29-4af4-a9eb-8d1603bc4942/2023-10-10-16-55-04_UMBRA-04/2023-10-10-16-55-04_UMBRA-04_CPHD.cphd",
      "type": "application/octet-stream",
      "title": "CPHD",
      "description": "https://nsgreg.nga.mil/doc/view?i=4638",
      "roles": [
        "data"
      ]
    },
    "GEC": {
      "href": "https://umbra-open-data-catalog.s3.amazonaws.com/sar-data/tasks/North Dakota State University Plot/9eca8179-ed29-4af4-a9eb-8d1603bc4942/2023-10-10-16-55-04_UMBRA-04/2023-10-10-16-55-04_UMBRA-04_GEC.tif",
      "type": "image/tiff; application=geotiff; profile=cloud-optimized",
      "title": "GEC",
      "roles": [
        "data",
        "overview"
      ]
    },
    "SICD": {
      "href": "https://umbra-open-data-catalog.s3.amazonaws.com/sar-data/tasks/North Dakota State University Plot/9eca8179-ed29-4af4-a9eb-8d1603bc4942/2023-10-10-16-55-04_UMBRA-04/2023-10-10-16-55-04_UMBRA-04_SICD.nitf",
      "type": "application/vnd.nitf",
      "title": "SICD",
      "description": "Sensor Independent Complex Data",
      "roles": [
        "data"
      ]
    },
    "SIDD": {
      "href": "https://umbra-open-data-catalog.s3.amazonaws.com/sar-data/tasks/North Dakota State University Plot/9eca8179-ed29-4af4-a9eb-8d1603bc4942/2023-10-10-16-55-04_UMBRA-04/2023-10-10-16-55-04_UMBRA-04_SIDD.nitf",
      "type": "application/vnd.nitf",
      "title": "SIDD",
      "description": "Sensor Independent Derived Data",
      "roles": [
        "data"
      ]
    }
  }
}