{
  "type": "Feature",
  "stac_version": "1.0.0",
  "stac_extensions": [
    "https://stac-extensions.github.io/view/v1.0.0/schema.json",
    "https://stac-extensions.github.io/sar/v1.0.0/schema.json"
  ],
  "id": "80cb2b7c-713d-4d2b-b8d2-edb2a3e5a23a",
  "geometry": {
    "type": "Polygon",
    "coordinates": [
      [
        [
          167.36822903576524,
          -77.54304258422513,
          2896.3538782531396
        ],
        [
          167.37846536112295,
          -77.53574351768998,
          2896.410408691503
        ],
        [
          167.38870189125873,
          -77.52844481295031,
          2896.5805444456637
        ],
        [
          167.3989147130832,
          -77.52114459435828,
          2896.863821635954
        ],
        [
          167.40912785589686,
          -77.5138446797144,
          2897.26071979478
        ],
        [
          167.35963732756295,
          -77.51060360718739,
          2896.4075621431693
        ],
        [
          167.31017224399469,
          -77.50735316425721,
          2895.798213615082
        ],
        [
          167.26072839954406,
          -77.50409612313749,
          2895.4325038166717
        ],
        [
          167.21130937897885,
          -77.50082984523608,
          2895.310605980456
        ],
        [
          167.1619148883274,
          -77.49755439449824,
          2895.432528684847
        ],
        [
          167.112558377749,
          -77.49426944574006,
          2895.798240451142
        ],
        [
          167.06321600985532,
          -77.49097312833732,
          2896.4079579459503
        ],
        [
          167.01390704241606,
          -77.48767016547323,
          2897.261218466796
        ],
        [
          167.00348623667034,
          -77.49495779785464,
          2896.864252751693
        ],
        [
          166.99307256052742,
          -77.50224037830014,
          2896.580695946701
        ],
        [
          166.9826267377899,
          -77.50952684160373,
          2896.410608389415
        ],
        [
          166.97218395282266,
          -77.5168110291794,
          2896.3537548556924
        ],
        [
          166.96171672754323,
          -77.52409373337623,
          2896.410524226725
        ],
        [
          166.95124849685917,
          -77.53137693297118,
          2896.5804443070665
        ],
        [
          166.94076935803818,
          -77.53865833106637,
          2896.863689831458
        ],
        [
          166.930261733348,
          -77.54594104326783,
          2897.2606766903773
        ],
        [
          166.979789654382,
          -77.54925884960372,
          2896.4072756739333
        ],
        [
          167.0293241662143,
          -77.55257066650574,
          2895.798120413907
        ],
        [
          167.0789005414444,
          -77.55587025776437,
          2895.4324023965746
        ],
        [
          167.12850157572407,
          -77.55916064624131,
          2895.3105119047686
        ],
        [
          167.17811374496162,
          -77.56244217919684,
          2895.4324421780184
        ],
        [
          167.2277612247644,
          -77.56571666468035,
          2895.7982521392405
        ],
        [
          167.2774379511553,
          -77.56897906994453,
          2896.4076688578352
        ],
        [
          167.3271368130092,
          -77.57223470006679,
          2897.2610194683075
        ],
        [
          167.33742092655302,
          -77.56493757357612,
          2896.864082392305
        ],
        [
          167.3477087469338,
          -77.55763823838429,
          2896.5806578202173
        ],
        [
          167.35796884572196,
          -77.55034020159057,
          2896.410469373688
        ],
        [
          167.36822903576524,
          -77.54304258422513,
          2896.3538782531396
        ]
      ]
    ]
  },
  "bbox": [
    166.930261733348,
    -77.57223470006679,
    167.40912785589686,
    -77.48767016547323
  ],
  "properties": {
    "created": "2024-12-17T09:52:35.382446Z",
    "updated": "2024-12-17T09:52:35.382446Z",
    "start_datetime": "2023-10-30T11:39:24Z",
    "end_datetime": "2023-10-30T11:39:29Z",
    "license": "CC-BY-4.0",
    "providers": [
      {
        "name": "umbra",
        "roles": [
          "host",
          "processor",
          "producer",
          "licensor"
        ],
        "url": "https://umbra.space"
      }
    ],
    "constellation": "umbra",
    "platform": "UMBRA_05",
    "mission": "umbra-sample-data",
    "view:incidence_angle": 41.885049989863354,
    "sar:instrument_mode": "SPOTLIGHT",
    "sar:frequency_band": "X",
    "sar:center_frequency": 9.800004769815132,
    "sar:polarizations": [
      "VV"
    ],
    "sar:product_type": "GEC",
    "sar:resolution_range": 0.32906969797149255,
    "sar:resolution_azimuth": 0.3246225079700795,
    "sar:looks_range": 1,
    "sar:looks_azimuth": 1,
    "sar:observation_direction": "left",
    "datetime": "2023-10-30T11:39:24Z"
  },
  "links": [
    {
      "rel": "root",
      "href": "../../../../catalog.json",
      "type": "application/json",
      "title": "Umbra Open SAR Data"
    },
    {
      "rel": "parent",
      "href": "../catalog.json",
      "type": "application/json",
      "title": "2023-10-30"
    }
  ],
  "assets": {
    "metadata": {
      "href": "http://umbra-open-data-catalog.s3.amazonaws.com/sar-data/tasks/Volcanoes/Erebus%2C%20Antarctica/ddadb6ca-1aaa-4aa5-99b6-8687b4bc2853/2023-10-30-11-39-23_UMBRA-05/2023-10-30-11-39-23_UMBRA-05_METADATA.json",
      "type": "application/json",
      "title": "metadata",
      "description": "Extended Umbra Metadata: https://docs.canopy.umbra.space/reference/get_schema",
      "roles": [
        "metadata"
      ]
    },
    "CPHD": {
      "href": "https://umbra-open-data-catalog.s3.amazonaws.com/sar-data/tasks/Volcanoes/Erebus, Antarctica/ddadb6ca-1aaa-4aa5-99b6-8687b4bc2853/2023-10-30-11-39-23_UMBRA-05/2023-10-30-11-39-23_UMBRA-05_CPHD.cphd",
      "type": "application/octet-stream",
      "title": "CPHD",
      "description": "https://nsgreg.nga.mil/doc/view?i=4638",
      "roles": [
        "data"
      ]
    },
    "GEC": {
      "href": "https://umbra-open-data-catalog.s3.amazonaws.com/sar-data/tasks/Volcanoes/Erebus, Antarctica/ddadb6ca-1aaa-4aa5-99b6-8687b4bc2853/2023-10-30-11-39-23_UMBRA-05/2023-10-30-11-39-23_UMBRA-05_GEC.tif",
      "type": "image/tiff; application=geotiff; profile=cloud-optimized",
      "title": "GEC",
      "roles": [
        "data",
        "overview"
      ]
    },
    "SICD": {
      "href": "https://umbra-open-data-catalog.s3.amazonaws.com/sar-data/tasks/Volcanoes/Erebus, Antarctica/ddadb6ca-1aaa-4aa5-99b6-8687b4bc2853/2023-10-30-11-39-23_UMBRA-05/2023-10-30-11-39-23_UMBRA-05_SICD.nitf",
      "type": "application/vnd.nitf",
      "title": "SICD",
      "description": "Sensor Independent Complex Data",
      "roles": [
        "data"
      ]
    },
    "SIDD": {
      "href": "https://umbra-open-data-catalog.s3.amazonaws.com/sar-data/tasks/Volcanoes/Erebus, Antarctica/ddadb6ca-1aaa-4aa5-99b6-8687b4bc2853/2023-10-30-11-39-23_UMBRA-05/2023-10-30-11-39-23_UMBRA-05_SIDD.nitf",
      "type": "application/vnd.nitf",
      "title": "SIDD",
      "description": "Sensor Independent Derived Data",
      "roles": [
        "data"
      ]
    }
  }
}