{
  "type": "Feature",
  "stac_version": "1.0.0",
  "stac_extensions": [
    "https://stac-extensions.github.io/view/v1.0.0/schema.json",
    "https://stac-extensions.github.io/sar/v1.0.0/schema.json"
  ],
  "id": "a43b7128-2d58-45c0-8ffc-07355faad6fb",
  "geometry": {
    "type": "Polygon",
    "coordinates": [
      [
        [
          169.469241663488,
          -19.498428110744943,
          110.24965436477214
        ],
        [
          169.46457454981578,
          -19.499314568228428,
          110.11267132591456
        ],
        [
          169.45990517030293,
          -19.500208695146597,
          110.01451118383557
        ],
        [
          169.45523036105695,
          -19.50109643753797,
          109.95576839335263
        ],
        [
          169.45056644121436,
          -19.50198213745917,
          109.93628558330238
        ],
        [
          169.44589288478207,
          -19.5028768589627,
          109.95572756789625
        ],
        [
          169.4412212517634,
          -19.503763846629735,
          110.01462793909013
        ],
        [
          169.43655311401767,
          -19.504650138138853,
          110.11264659184963
        ],
        [
          169.43188111452474,
          -19.505537072488245,
          110.24994342122227
        ],
        [
          169.43282012383563,
          -19.509966980714147,
          110.11188149359077
        ],
        [
          169.43375763844594,
          -19.51439728257158,
          110.0133084077388
        ],
        [
          169.434693660785,
          -19.518827987994857,
          109.95422681607306
        ],
        [
          169.43563391167115,
          -19.52325071409731,
          109.93439763318747
        ],
        [
          169.4365669471131,
          -19.527682254573584,
          109.95424610562623
        ],
        [
          169.43750583917202,
          -19.53211287152432,
          110.01335023250431
        ],
        [
          169.4384415961657,
          -19.53653688678754,
          110.11177689954638
        ],
        [
          169.43938485568162,
          -19.540967024441645,
          110.24958903435618
        ],
        [
          169.44405013387282,
          -19.54007829229825,
          110.11218555923551
        ],
        [
          169.44872624471802,
          -19.53918748645011,
          110.01369973551482
        ],
        [
          169.45339850385218,
          -19.538297335030524,
          109.95452689472586
        ],
        [
          169.45806690776905,
          -19.537407838918536,
          109.93457107804716
        ],
        [
          169.4627404801543,
          -19.53652464901199,
          109.95405057724565
        ],
        [
          169.46740854166092,
          -19.535635091131287,
          110.01242782268673
        ],
        [
          169.4720801274786,
          -19.534744817332314,
          110.11004376038909
        ],
        [
          169.47674786613476,
          -19.533855197806503,
          110.24674020148814
        ],
        [
          169.4758112755987,
          -19.529426871212213,
          110.10924113448709
        ],
        [
          169.47487320989976,
          -19.52499899054476,
          110.01109537295997
        ],
        [
          169.4739336664198,
          -19.520571545869014,
          109.95229860860854
        ],
        [
          169.47299840855416,
          -19.516136152948008,
          109.93309049960226
        ],
        [
          169.47205591163961,
          -19.511709552271753,
          109.95304283872247
        ],
        [
          169.47111931672842,
          -19.507282005420965,
          110.01257988996804
        ],
        [
          169.47018123482567,
          -19.50285486156712,
          110.11145129520446
        ],
        [
          169.469241663488,
          -19.498428110744943,
          110.24965436477214
        ]
      ]
    ]
  },
  "bbox": [
    169.43188111452474,
    -19.540967024441645,
    169.47674786613476,
    -19.498428110744943
  ],
  "properties": {
    "created": "2024-12-17T09:51:27.812416Z",
    "updated": "2024-12-17T09:51:27.812416Z",
    "start_datetime": "2023-03-22T10:09:33.683824Z",
    "end_datetime": "2023-03-22T10:09:34.979447Z",
    "license": "CC-BY-4.0",
    "providers": [
      {
        "name": "umbra",
        "roles": [
          "host",
          "processor",
          "producer",
          "licensor"
        ],
        "url": "https://umbra.space"
      }
    ],
    "constellation": "umbra",
    "platform": "UMBRA_04",
    "mission": "umbra-sample-data",
    "view:incidence_angle": 38.535672685161074,
    "sar:instrument_mode": "SPOTLIGHT",
    "sar:frequency_band": "X",
    "sar:center_frequency": 9.599994967575187,
    "sar:polarizations": [
      "VV"
    ],
    "sar:product_type": "GEC",
    "sar:resolution_range": 0.886158257374729,
    "sar:resolution_azimuth": 0.905939830079356,
    "sar:looks_range": 1,
    "sar:looks_azimuth": 1,
    "sar:observation_direction": "left",
    "datetime": "2023-03-22T10:09:33.683824Z"
  },
  "links": [
    {
      "rel": "root",
      "href": "../../../../catalog.json",
      "type": "application/json",
      "title": "Umbra Open SAR Data"
    },
    {
      "rel": "parent",
      "href": "../catalog.json",
      "type": "application/json",
      "title": "2023-03-22"
    }
  ],
  "assets": {
    "metadata": {
      "href": "http://umbra-open-data-catalog.s3.amazonaws.com/sar-data/tasks/Tanna%20Island%2C%20Vanuatu/075b692c-656e-4561-8376-5b53b103514e/2023-03-22-10-09-31_UMBRA-04/2023-03-22-10-09-31_UMBRA-04_METADATA.json",
      "type": "application/json",
      "title": "metadata",
      "description": "Extended Umbra Metadata: https://docs.canopy.umbra.space/reference/get_schema",
      "roles": [
        "metadata"
      ]
    },
    "CPHD": {
      "href": "https://umbra-open-data-catalog.s3.amazonaws.com/sar-data/tasks/Tanna Island, Vanuatu/075b692c-656e-4561-8376-5b53b103514e/2023-03-22-10-09-31_UMBRA-04/2023-03-22-10-09-31_UMBRA-04_CPHD.cphd",
      "type": "application/octet-stream",
      "title": "CPHD",
      "description": "https://nsgreg.nga.mil/doc/view?i=4638",
      "roles": [
        "data"
      ]
    },
    "GEC": {
      "href": "https://umbra-open-data-catalog.s3.amazonaws.com/sar-data/tasks/Tanna Island, Vanuatu/075b692c-656e-4561-8376-5b53b103514e/2023-03-22-10-09-31_UMBRA-04/2023-03-22-10-09-31_UMBRA-04_GEC.tif",
      "type": "image/tiff; application=geotiff; profile=cloud-optimized",
      "title": "GEC",
      "roles": [
        "data",
        "overview"
      ]
    },
    "SICD": {
      "href": "https://umbra-open-data-catalog.s3.amazonaws.com/sar-data/tasks/Tanna Island, Vanuatu/075b692c-656e-4561-8376-5b53b103514e/2023-03-22-10-09-31_UMBRA-04/2023-03-22-10-09-31_UMBRA-04_SICD.nitf",
      "type": "application/vnd.nitf",
      "title": "SICD",
      "description": "Sensor Independent Complex Data",
      "roles": [
        "data"
      ]
    },
    "SIDD": {
      "href": "https://umbra-open-data-catalog.s3.amazonaws.com/sar-data/tasks/Tanna Island, Vanuatu/075b692c-656e-4561-8376-5b53b103514e/2023-03-22-10-09-31_UMBRA-04/2023-03-22-10-09-31_UMBRA-04_SIDD.nitf",
      "type": "application/vnd.nitf",
      "title": "SIDD",
      "description": "Sensor Independent Derived Data",
      "roles": [
        "data"
      ]
    }
  }
}