{
  "type": "Feature",
  "stac_version": "1.0.0",
  "stac_extensions": [
    "https://stac-extensions.github.io/view/v1.0.0/schema.json",
    "https://stac-extensions.github.io/sar/v1.0.0/schema.json"
  ],
  "id": "c83106b8-ea55-4e0b-b472-25b91111eab2",
  "geometry": {
    "type": "Polygon",
    "coordinates": [
      [
        [
          105.99681107818819,
          -6.292943479786994,
          1770.8216237537563
        ],
        [
          106.00069908942376,
          -6.3012497015197715,
          1770.9055791096762
        ],
        [
          106.00458821431143,
          -6.309555189065986,
          1771.1516201030463
        ],
        [
          106.00847847450832,
          -6.317859985979195,
          1771.5597375864163
        ],
        [
          106.01236989144577,
          -6.326164135877825,
          1772.1299258954823
        ],
        [
          106.02566807207856,
          -6.31992935544588,
          1770.6761451801285
        ],
        [
          106.0389665969511,
          -6.313692035589901,
          1769.636731185019
        ],
        [
          106.05226692127074,
          -6.307455185145381,
          1769.0120493303984
        ],
        [
          106.06556461496972,
          -6.301218648972904,
          1768.8020901083946
        ],
        [
          106.07886357450298,
          -6.294981101442504,
          1769.006799547933
        ],
        [
          106.09216006685664,
          -6.288743886314353,
          1769.626074933447
        ],
        [
          106.10545797864378,
          -6.282505678589461,
          1770.6601043026894
        ],
        [
          106.11875288618309,
          -6.276266306545068,
          1772.1084578931332
        ],
        [
          106.1148631931393,
          -6.267961569920456,
          1771.5435648383573
        ],
        [
          106.11097174133569,
          -6.259658996149204,
          1771.140624716878
        ],
        [
          106.10708090340236,
          -6.251354178549664,
          1770.899975894019
        ],
        [
          106.10318756578697,
          -6.24304993820097,
          1770.821259896271
        ],
        [
          106.09930000534229,
          -6.234745050516305,
          1770.9053684584796
        ],
        [
          106.09540611911302,
          -6.2264420171328885,
          1771.1509484788403
        ],
        [
          106.09151726075753,
          -6.218136736773721,
          1771.5593539103866
        ],
        [
          106.08762654725216,
          -6.209833394620952,
          1772.1296141473576
        ],
        [
          106.07433194186753,
          -6.216069760299024,
          1770.6759167071432
        ],
        [
          106.06103515330368,
          -6.222306738065291,
          1769.6366687119007
        ],
        [
          106.04774061329718,
          -6.228544457555629,
          1769.0120180435479
        ],
        [
          106.03444301079224,
          -6.23478126325896,
          1768.8020719224587
        ],
        [
          106.02114678595419,
          -6.241017287225585,
          1769.0067669134587
        ],
        [
          106.00784805051921,
          -6.247253884879887,
          1769.6262177508324
        ],
        [
          105.99455053509186,
          -6.25348968197484,
          1770.6602668603882
        ],
        [
          105.98125345427417,
          -6.259723177298974,
          1772.1089078318328
        ],
        [
          105.985144156278,
          -6.268028537408912,
          1771.543580327183
        ],
        [
          105.98903206783352,
          -6.276334361740836,
          1771.1408464256674
        ],
        [
          105.9929210343675,
          -6.284639328080849,
          1770.900200610049
        ],
        [
          105.99681107818819,
          -6.292943479786994,
          1770.8216237537563
        ]
      ]
    ]
  },
  "bbox": [
    105.98125345427417,
    -6.326164135877825,
    106.11875288618309,
    -6.209833394620952
  ],
  "properties": {
    "created": "2024-12-17T09:52:38.400678Z",
    "updated": "2024-12-17T09:52:38.400678Z",
    "start_datetime": "2023-11-15T14:49:09Z",
    "end_datetime": "2023-11-15T14:49:16.321440Z",
    "license": "CC-BY-4.0",
    "providers": [
      {
        "name": "umbra",
        "roles": [
          "host",
          "processor",
          "producer",
          "licensor"
        ],
        "url": "https://umbra.space"
      }
    ],
    "constellation": "umbra",
    "platform": "UMBRA_05",
    "mission": "umbra-sample-data",
    "view:incidence_angle": 52.05338704997311,
    "sar:instrument_mode": "SPOTLIGHT",
    "sar:frequency_band": "X",
    "sar:center_frequency": 9.599998456542382,
    "sar:polarizations": [
      "VV"
    ],
    "sar:product_type": "GEC",
    "sar:resolution_range": 0.4451200538848664,
    "sar:resolution_azimuth": 0.20144213714319154,
    "sar:looks_range": 1,
    "sar:looks_azimuth": 2,
    "sar:observation_direction": "right",
    "datetime": "2023-11-15T14:49:09Z"
  },
  "links": [
    {
      "rel": "root",
      "href": "../../../../catalog.json",
      "type": "application/json",
      "title": "Umbra Open SAR Data"
    },
    {
      "rel": "parent",
      "href": "../catalog.json",
      "type": "application/json",
      "title": "2023-11-15"
    }
  ],
  "assets": {
    "metadata": {
      "href": "http://umbra-open-data-catalog.s3.amazonaws.com/sar-data/tasks/Volcanoes/Karang%2C%20Indonesia/458d6e4d-a88a-482b-9232-2a924d8ee2ee/2023-11-15-14-49-08_UMBRA-05/2023-11-15-14-49-08_UMBRA-05_METADATA.json",
      "type": "application/json",
      "title": "metadata",
      "description": "Extended Umbra Metadata: https://docs.canopy.umbra.space/reference/get_schema",
      "roles": [
        "metadata"
      ]
    },
    "CPHD": {
      "href": "https://umbra-open-data-catalog.s3.amazonaws.com/sar-data/tasks/Volcanoes/Karang, Indonesia/458d6e4d-a88a-482b-9232-2a924d8ee2ee/2023-11-15-14-49-08_UMBRA-05/2023-11-15-14-49-08_UMBRA-05_CPHD.cphd",
      "type": "application/octet-stream",
      "title": "CPHD",
      "description": "https://nsgreg.nga.mil/doc/view?i=4638",
      "roles": [
        "data"
      ]
    },
    "GEC": {
      "href": "https://umbra-open-data-catalog.s3.amazonaws.com/sar-data/tasks/Volcanoes/Karang, Indonesia/458d6e4d-a88a-482b-9232-2a924d8ee2ee/2023-11-15-14-49-08_UMBRA-05/2023-11-15-14-49-08_UMBRA-05_GEC.tif",
      "type": "image/tiff; application=geotiff; profile=cloud-optimized",
      "title": "GEC",
      "roles": [
        "data",
        "overview"
      ]
    },
    "SICD": {
      "href": "https://umbra-open-data-catalog.s3.amazonaws.com/sar-data/tasks/Volcanoes/Karang, Indonesia/458d6e4d-a88a-482b-9232-2a924d8ee2ee/2023-11-15-14-49-08_UMBRA-05/2023-11-15-14-49-08_UMBRA-05_SICD.nitf",
      "type": "application/vnd.nitf",
      "title": "SICD",
      "description": "Sensor Independent Complex Data",
      "roles": [
        "data"
      ]
    },
    "SIDD": {
      "href": "https://umbra-open-data-catalog.s3.amazonaws.com/sar-data/tasks/Volcanoes/Karang, Indonesia/458d6e4d-a88a-482b-9232-2a924d8ee2ee/2023-11-15-14-49-08_UMBRA-05/2023-11-15-14-49-08_UMBRA-05_SIDD.nitf",
      "type": "application/vnd.nitf",
      "title": "SIDD",
      "description": "Sensor Independent Derived Data",
      "roles": [
        "data"
      ]
    }
  }
}